fastzdp_rand/__init__.py
fastzdp_rand/last_name.py
fastzdp_rand-0.1.0.dist-info/LICENSE
fastzdp_rand-0.1.0.dist-info/METADATA
fastzdp_rand-0.1.0.dist-info/WHEEL
fastzdp_rand-0.1.0.dist-info/RECORD
